odoo8_addon_document_sftp-8.0.1.0.0.99.dev3-py2.7-nspkg.pth
odoo_addons/document_sftp/document_sftp_handle.py
odoo_addons/document_sftp/__openerp__.py
odoo_addons/document_sftp/document_sftp_transport.py
odoo_addons/document_sftp/hooks.py
odoo_addons/document_sftp/__init__.py
odoo_addons/document_sftp/document_sftp_server.py
odoo_addons/document_sftp/README.rst
odoo_addons/document_sftp/document_sftp_sftp_server.py
odoo_addons/document_sftp/models/document_sftp_root_by_model.py
odoo_addons/document_sftp/models/document_sftp.py
odoo_addons/document_sftp/models/document_sftp_root.py
odoo_addons/document_sftp/models/__init__.py
odoo_addons/document_sftp/models/res_users.py
odoo_addons/document_sftp/views/res_users.xml
odoo_addons/document_sftp/data/ir_config_parameter.xml
odoo_addons/document_sftp/tests/test_document_sftp.py
odoo_addons/document_sftp/tests/__init__.py
odoo_addons/document_sftp/demo/demo.key
odoo_addons/document_sftp/demo/res_users.xml
odoo_addons/document_sftp/static/description/icon.png
odoo8_addon_document_sftp-8.0.1.0.0.99.dev3.dist-info/top_level.txt
odoo8_addon_document_sftp-8.0.1.0.0.99.dev3.dist-info/WHEEL
odoo8_addon_document_sftp-8.0.1.0.0.99.dev3.dist-info/RECORD
odoo8_addon_document_sftp-8.0.1.0.0.99.dev3.dist-info/metadata.json
odoo8_addon_document_sftp-8.0.1.0.0.99.dev3.dist-info/DESCRIPTION.rst
odoo8_addon_document_sftp-8.0.1.0.0.99.dev3.dist-info/METADATA
odoo8_addon_document_sftp-8.0.1.0.0.99.dev3.dist-info/namespace_packages.txt
