Metadata-Version: 2.0
Name: odoo8-addon-document-sftp
Version: 8.0.1.0.0.99.dev3
Summary: Access your documents via SFTP
Home-page: UNKNOWN
Author: Therp BV,Odoo Community Association (OCA)
Author-email: support@odoo-community.org
License: AGPL-3
Platform: UNKNOWN
Requires-Dist: odoo (<9.0a,>=8.0a)
Requires-Dist: paramiko
Classifier: Programming Language :: Python :: 2.7
Classifier: Framework :: Odoo
Classifier: License :: OSI Approved :: GNU Affero General Public License v3
